litematica_command_gen/__init__.py
litematica_command_gen/__main__.py
litematica_command_gen/cli.py
litematica_command_gen/command_generator.py
litematica_command_gen/data/test.csv
litematica_command_gen/mc_id_converter/__init__.py
litematica_command_gen/mc_id_converter/__main__.py
litematica_command_gen/mc_id_converter/converter.py
litematica_command_gen/mc_id_converter/data/block_data.html
litematica_command_gen-0.1.0.dist-info/LICENSE
litematica_command_gen-0.1.0.dist-info/METADATA
litematica_command_gen-0.1.0.dist-info/WHEEL
litematica_command_gen-0.1.0.dist-info/entry_points.txt
litematica_command_gen-0.1.0.dist-info/top_level.txt
litematica_command_gen-0.1.0.dist-info/RECORD
