Metadata-Version: 2.1
Name: litematica-command-gen
Version: 0.1.0
Summary: A CLI application to generate give commands for shulker boxes full of items for litematica projects. Used by the lazy survival player :).
Home-page: https://github.com/appcreatorguy/litematica_command_gen
Author: Manas Mengle
Author-email: manmenonsense@gmail.com
License: GNU General Public License v3
Keywords: litematica_command_gen
Platform: UNKNOWN
Classifier: Development Status :: 2 - Pre-Alpha
Classifier: Intended Audience :: Developers
Classifier: License :: OSI Approved :: GNU General Public License v3 (GPLv3)
Classifier: Natural Language :: English
Classifier: Programming Language :: Python :: 3
Classifier: Programming Language :: Python :: 3.6
Classifier: Programming Language :: Python :: 3.7
Classifier: Programming Language :: Python :: 3.8
Classifier: Programming Language :: Python :: 3.9
Requires-Python: >=3.6
Requires-Dist: pandas (==1.3.3)
Requires-Dist: mecha (==0.5.0)
Requires-Dist: docopt (==0.6.2)
